reconciliacion/supcapa4.v
module carrier_indication(
    input clk,
    input crs,
    output reg pls_carrier_indication
);
always @(posedge clk) begin
    if (crs) begin
        pls_carrier_indication = 1;
    end
    else
    pls_carrier_indication = 0;
end
endmodule

reconciliacion/supcapa3.v
//capa del receptor
module data_indication(
    input [7:0]rxd,
    input rx_er,
    input rx_clk,
    input rx_dv,
    output reg [2:0]data_indication,// one,zero,extend en ese orden
    output reg data_valid
);
//inicio de la lógica
always @(posedge rx_clk) begin
    //Carrier extend
    if (rx_dv == 0 && rx_er == 1 && rxd == 8'h0F) begin
        data_indication = 3'b001;
        data_valid =1;
    end//fin del if
    //Carrier extend error
    else if (rx_dv == 0 && rx_er == 1 && rxd == 8'h1F)begin
      data_indication = 3'b110;//zero y one activados
      data_valid = 1;
    end//fin del else if
    //normal data reception
    else if (rx_dv == 1 && rx_er == 0 && rxd != 8'h0F)begin
        data_indication = 3'b110;
        data_valid = 1;
    end//fin del else if
    //data reception error
    else if (rx_dv == 1 && rx_er == 1 && rxd != 8'h0F)begin
      data_indication = 3'b110;
      data_valid = 0;
    end//fin del else if
end//fin del always

endmodule //fin del modulo

reconciliacion/supcapa2.v
module supcapa2(
    input clk,
    input col,
    output reg pls_signal_indication 
);

//empezamos con la lógica
always @(posedge clk) begin
    if (!col)
    pls_signal_indication = 0;
    else
    pls_signal_indication = 1;
end//fin del always

endmodule

reconciliacion/supcapa1v2.v
// esta capa hace referencia a la capa1 pero con 
// valores tipo one hot
//copia de la capa anterior

module capa1v2(
input reset,
input clk,
input [4:0]pls_data_request,
output reg gtx_clk,
output reg [7:0]txd,
output reg tx_en,
output reg tx_er);

//ocupamos para el reloj
reg [1:0]count;
reg [2:0]h;

//inicializamos el reloj
initial begin
count =1;
h=2;
end
//código para nuestra salida del gtx clk, con modificación de frecuencias
always @(posedge clk)begin
if (reset)begin
count =1;
gtx_clk = 0;
end
else if(count==(h/2))begin
count =1;
gtx_clk = ~gtx_clk;
end
end

//Código regido según la tabla de las salidas 
//correspondientes
always @(posedge gtx_clk)begin
if (reset)begin
tx_en = 0;
tx_er = 0;
txd = 0;
end//termina el if
//cero
else if ( pls_data_request == 5'b00001)begin
tx_en = 1;
tx_er = 0;
txd = 8'h4F;
end//termina else if
//uno
else if(pls_data_request == 5'b00010)begin
tx_en = 1;
tx_er = 0;
txd = 8'h3F;
end//termina else if
//extend error
else if(pls_data_request == 5'b00100)begin
tx_en = 0;
tx_er = 1;
txd = 8'h1F;
end//termina else if
//extend
else if(pls_data_request == 5'b01000)begin
tx_en = 0;
tx_er = 1;
txd = 8'h0F;
end//termina else if
//data complete
else if(pls_data_request == 5'b10000)begin
tx_en = 0;
tx_er = 0;
txd = 8'h5F;
end //termina el else if

end //termina el always

endmodule // termina el modulo

reconciliacion/recon_layer.v

//aqui iran todos los modulos puestos junto con testbench
`include "supcapa1v2.v"
`include "supcapa2.v"
`include "supcapa3.v"
`include "supcapa4.v"
module recon_final;
//tb_Capa1
reg reset;
reg clk;
reg [4:0]pls_data_request;
wire gtx_clk;
wire [7:0]txd;
wire tx_en;
wire tx_er;
//tbcapa2
reg col;
wire pls_signal_indication;
//tb_Capa3
reg [7:0]rxd;
reg rx_er;
reg rx_clk;
reg rx_dv;
wire data_valid;
wire [2:0]data_indication;
//tb_capa4
reg crs;
wire pls_carrier_indication;

//empezamos a intanciar los modulos

capa1v2 dut(
  .clk (clk),
  .reset (reset),
  .txd (txd),
  .tx_en (tx_en),
  .tx_er (tx_er),
  .gtx_clk (gtx_clk),
  .pls_data_request (pls_data_request)
);

supcapa2 dut1(
    .clk (clk),
    .col (col),
    .pls_signal_indication (pls_signal_indication)
);

data_indication dut2(
  .rxd (rxd),
  .rx_clk (rx_clk),
  .rx_dv (rx_dv),
  .rx_er (rx_er),
  .data_valid (data_valid),
  .data_indication (data_indication)
);

carrier_indication dut3(
    .clk (clk),
    .crs (crs),
    .pls_carrier_indication (pls_carrier_indication)
);

initial begin
  $dumpfile("tb_recon.vcd");
	$dumpvars(-1, dut);
    $dumpvars(-1, dut1);
    $dumpvars(-1, dut2);
    $dumpvars(-1, dut3);
end

always begin
 #5 clk = ~clk; 
end

always begin
 #10 rx_clk = ~rx_clk; 
end

initial begin
  //inicial capa de todos
  
  clk =1;
  col = 0;
  reset =1;
  rx_clk =0;
  rxd = 0;
  rx_er =0;
  rx_dv =0;
   crs = 1;
  #10 reset =0;
  //supcapa1
  #20 pls_data_request = 5'b00001;//cero
  #20 pls_data_request = 5'b00010;//uno
  #20 pls_data_request = 5'b00100;//extend error
  #20 pls_data_request = 5'b01000;//extend
  //supcapa2
  #20 col = 1;
  #20 col = 0;
  #20 col = 1;
  //supcapa3
  #20 rx_dv = 0; rx_er = 1; rxd =8'h0F ;
  #20 rx_dv = 0; rx_er = 1; rxd =8'h1F ;
  #20 rx_dv = 1; rx_er = 0; rxd =8'h4F ;
  #20 rx_dv = 1; rx_er = 1; rxd =8'h5F ;
  //supcapa4
  #20 crs = 1;  
  #20 crs = 0;
  #20 crs = 1;
end

initial #600 $finish;
endmodule

reconciliacion/tb_recon.vcd
$date
	Sat Nov 19 22:52:39 2022
$end
$version
	Icarus Verilog
$end
$timescale
	1s
$end
$scope module recon_final $end
$scope module dut $end
$var wire 1 ! clk $end
$var wire 5 " pls_data_request [4:0] $end
$var wire 1 # reset $end
$var reg 2 $ count [1:0] $end
$var reg 1 % gtx_clk $end
$var reg 3 & h [2:0] $end
$var reg 1 ' tx_en $end
$var reg 1 ( tx_er $end
$var reg 8 ) txd [7:0] $end
$upscope $end
$upscope $end
$scope module recon_final $end
$scope module dut1 $end
$var wire 1 ! clk $end
$var wire 1 * col $end
$var reg 1 + pls_signal_indication $end
$upscope $end
$upscope $end
$scope module recon_final $end
$scope module dut2 $end
$var wire 1 , rx_clk $end
$var wire 1 - rx_dv $end
$var wire 1 . rx_er $end
$var wire 8 / rxd [7:0] $end
$var reg 3 0 data_indication [2:0] $end
$var reg 1 1 data_valid $end
$upscope $end
$upscope $end
$scope module recon_final $end
$scope module dut3 $end
$var wire 1 ! clk $end
$var wire 1 2 crs $end
$var reg 1 3 pls_carrier_indication $end
$upscope $end
$upscope $end
$enddefinitions $end
#0
$dumpvars
13
12
x1
bx 0
b0 /
0.
0-
0,
0+
0*
bx )
x(
x'
b10 &
0%
b1 $
1#
bx "
1!
$end
#5
0!
#10
1%
1!
0#
1,
#15
0!
#20
0%
1!
0,
#25
0!
#30
b1001111 )
0(
1'
1%
1!
1,
b1 "
#35
0!
#40
0%
1!
0,
#45
0!
#50
b111111 )
1%
1!
1,
b10 "
#55
0!
#60
0%
1!
0,
#65
0!
#70
b11111 )
1(
0'
1%
1!
1,
b100 "
#75
0!
#80
0%
1!
0,
#85
0!
#90
b1111 )
1%
1!
1,
b1000 "
#95
0!
#100
0%
1!
0,
#105
0!
#110
1+
1%
1!
1,
1*
#115
0!
#120
0%
1!
0,
#125
0!
#130
0+
1%
1!
1,
0*
#135
0!
#140
0%
1!
0,
#145
0!
#150
1+
1%
1!
1,
1*
#155
0!
#160
0%
1!
0,
#165
0!
#170
1%
11
b1 0
1!
1,
b1111 /
1.
#175
0!
#180
0%
1!
0,
#185
0!
#190
1%
b110 0
1!
1,
b11111 /
#195
0!
#200
0%
1!
0,
#205
0!
#210
1%
1!
1,
b1001111 /
0.
1-
#215
0!
#220
0%
1!
0,
#225
0!
#230
1%
01
1!
1,
b1011111 /
1.
#235
0!
#240
0%
1!
0,
#245
0!
#250
1%
1!
1,
#255
0!
#260
0%
1!
0,
#265
0!
#270
03
1%
1!
1,
02
#275
0!
#280
0%
1!
0,
#285
0!
#290
13
1%
1!
1,
12
