PMA/piso.v


/*
******************************************************************************
*
*  Filename     :   piso.v
*i
*  Description  :   This module takes a parallel input and generates serial output.
                    For this module I adjoin a testbench together with its stimulations 
                    referenced as "piso_tb.v" to output a vvp file and check its functionality.
*
*  Author       :   Jhon Gaitan Aguilar
*                   <JHON.GAITAN@ucr.ac.cr>
*
*  License      :   This program is free software: you can redistribute it and/or modify
*                   it under the terms of the GNU General Public License as published by
*                   the Free Software Foundation, either version 3 of the License, or
*                   (at your option) any later version.
*
*                   This program is distributed in the hope that it will be useful,
*                   but WITHOUT ANY WARRANTY; without even the implied warranty of
*                   MERCHANTABILITY or FITNESS FOR A PARTICULAR PURPOSE.  See the
*                   GNU General Public License for more details.
*
*                   You should have received a copy of the GNU General Public License
*                   along with this program.  If not, see <http://www.gnu.org/licenses/>.
*  
*  Created      :   11/18/2022
*
******************************************************************************
*/
module piso(
    //Declare Inputs here
    input clk, //A global variable that works in the whole circuit.
    input reset,//A control signal of this module
    input [9:0]parallel_in, //This is the parallel bitstream coming from tx_code-group
    input s_start,
    //Desclare Outputs here
    output reg s_out);//This is the serial output chain towards pmd_unitdata.request

//Declare parameters here
localparam length = 10;//Length of the vector. in this case is 10-bit vector from PCS sublayer
//Declare Regsiters here
reg [9:0] temp;// A shift register that stores the bits to output as serial bistream.
//Declare Wires here 

//sesibility list
always @(posedge clk) begin
    //Set input to LOW
    if (reset==1)begin
        s_out = 0;
        temp = parallel_in;
    end
    else if(s_start == 1)begin
        s_out = temp[9];
        temp = {temp[9:0], 1'b0};
    end
end
endmodule

PMA/piso_tb.v
`timescale 1ps/1ps
`include "piso.v"
module piso_tb;
localparam length = 10;//Length of the vector. in this case is 10-bit vector from PCS sublayer
    //declare wires here
    //wire s_out;
    //declare registers here
    reg clk;
    reg reset;
    reg s_start;
    reg [9:0]parallel_in;
    reg [9:0] temp;
    
initial begin
	$dumpfile("PISO.vcd");
	$dumpvars(-1, uut);
end


//instantiate
piso uut(
    .clk (clk),
    .reset (reset),
    .s_start (s_start),
    .parallel_in (parallel_in)
    //.s_out (s_out)
    );


//clock toggle
always begin
    #1 clk = ~clk;
end
initial begin
    s_start = 0;
    clk = 0;
    #2 parallel_in = 10'b1010101111;
    reset = 1;
    #2 reset = 0;
    s_start =1;
end 
initial #50 $finish;
endmodule

PMA/PISO.vcd
$date
	Sun Nov 20 21:06:19 2022
$end
$version
	Icarus Verilog
$end
$timescale
	1ps
$end
$scope module piso_tb $end
$scope module uut $end
$var wire 1 ! clk $end
$var wire 10 " parallel_in [9:0] $end
$var wire 1 # reset $end
$var wire 1 $ s_start $end
$var reg 1 % s_out $end
$var reg 10 & temp [9:0] $end
$upscope $end
$upscope $end
$enddefinitions $end
#0
$dumpvars
bx &
x%
0$
x#
bx "
0!
$end
#1
1!
#2
0!
1#
b1010101111 "
#3
b1010101111 &
0%
1!
#4
0!
1$
0#
#5
b101011110 &
1%
1!
#6
0!
#7
b1010111100 &
0%
1!
#8
0!
#9
b101111000 &
1%
1!
#10
0!
#11
b1011110000 &
0%
1!
#12
0!
#13
b111100000 &
1%
1!
#14
0!
#15
b1111000000 &
0%
1!
#16
0!
#17
b1110000000 &
1%
1!
#18
0!
#19
b1100000000 &
1!
#20
0!
#21
b1000000000 &
1!
#22
0!
#23
b0 &
1!
#24
0!
#25
0%
1!
