PMA/sipo.v
/*
******************************************************************************
*
*  Filename     :   sipo.v
*i
*  Description  :   This module takes a serial input and generates parallel output.
                    For this module I adjoin a testbench together with its stimulations 
                    referenced as "sipo_tb.v" to output a vvp file and checking its functionality.
*
*  Author       :   Jhon Gaitan Aguilar
*                   <JHON.GAITAN@ucr.ac.cr>
*
*  License      :   This program is free software: you can redistribute it and/or modify
*                   it under the terms of the GNU General Public License as published by
*                   the Free Software Foundation, either version 3 of the License, or
*                   (at your option) any later version.
*
*                   This program is distributed in the hope that it will be useful,
*                   but WITHOUT ANY WARRANTY; without even the implied warranty of
*                   MERCHANTABILITY or FITNESS FOR A PARTICULAR PURPOSE.  See the
*                   GNU General Public License for more details.
*
*                   You should have received a copy of the GNU General Public License
*                   along with this program.  If not, see <http://www.gnu.org/licenses/>.
*  
*  Created      :   11/18/2022
*
******************************************************************************
*/
module sipo(
//Declare Inputs here
    input clk, //A global variable that works in the whole circuit.
    input reset,//A control signal of this module
    input s_in,
    //Desclare Outputs here
    output reg[9:0]parallel_out); //This is the parallel bitstream coming from rx_code-group
//Declare parameters here

//Declare Regsiters here
reg [9:0] temp_2;// A  shift register that stores the bits to output as parallel bistream.
//Declare Wires here 
//sesisbility list
always @(posedge clk) begin
    if (reset == 1)
    //Write to output
    parallel_out <= 10'b0;

    else if(reset == 0)begin
      temp_2 <= temp_2>>1;
      temp_2[9] <= s_in;//From [9] fill out with serialIinput inpit (s_in)||||tx_bit
    end
    if (temp_2[0] == 1'b0 || temp_2[0] == 1'b1) begin
        parallel_out = temp_2; 
    end
end
endmodule

PMA/sipo_tb.v
`timescale 1ps/1ps
`include "sipo.v"

module sipo_tb;
    //declare wires here
    wire [9:0]parallel_out;
    //declare registers here
    reg clk;
    reg reset;
    reg s_in;
    reg [9:0] temp_2;
    //reg [9:0] parallel_out;

    //clock toggle
always begin
    #1 clk = ~clk;
end

sipo uut(
    .clk (clk),
    .reset (reset),
    .s_in (s_in),
    .parallel_out (parallel_out));

initial begin
    reset =1;
    clk = 0;
    s_in =1;
    #20 reset =0;
    #20 s_in = 1;
    #20 s_in = 1;
    #20 s_in = 1;
    #20 s_in = 0;
    #20 s_in = 0;
    #20 s_in = 1;
    #20 s_in = 1;
    #20 s_in = 1;
    #20 s_in = 1;
    #20 s_in = 1;

end
initial  begin
    $dumpfile("SIPO.vcd");
	$dumpvars(-1, uut);
end

initial #250 $finish;
endmodule

PMA/SIPO.vcd
$date
	Sun Nov 20 21:46:57 2022
$end
$version
	Icarus Verilog
$end
$timescale
	1ps
$end
$scope module sipo_tb $end
$scope module uut $end
$var wire 1 ! clk $end
$var wire 1 " reset $end
$var wire 1 # s_in $end
$var reg 10 $ parallel_out [9:0] $end
$var reg 10 % temp_2 [9:0] $end
$upscope $end
$upscope $end
$enddefinitions $end
#0
$dumpvars
bx %
bx $
1#
1"
0!
$end
#1
b0 $
1!
#2
0!
#3
1!
#4
0!
#5
1!
#6
0!
#7
1!
#8
0!
#9
1!
#10
0!
#11
1!
#12
0!
#13
1!
#14
0!
#15
1!
#16
0!
#17
1!
#18
0!
#19
1!
#20
0!
0"
#21
b1xxxxxxxxx %
1!
#22
0!
#23
b11xxxxxxxx %
1!
#24
0!
#25
b111xxxxxxx %
1!
#26
0!
#27
b1111xxxxxx %
1!
#28
0!
#29
b11111xxxxx %
1!
#30
0!
#31
b111111xxxx %
1!
#32
0!
#33
b1111111xxx %
1!
#34
0!
#35
b11111111xx %
1!
#36
0!
#37
b111111111x %
1!
#38
0!
#39
b1111111111 %
1!
#40
0!
#41
b1111111111 %
b1111111111 $
1!
#42
0!
#43
b1111111111 %
1!
#44
0!
#45
b1111111111 %
1!
#46
0!
#47
b1111111111 %
1!
#48
0!
#49
b1111111111 %
1!
#50
0!
#51
b1111111111 %
1!
#52
0!
#53
b1111111111 %
1!
#54
0!
#55
b1111111111 %
1!
#56
0!
#57
b1111111111 %
1!
#58
0!
#59
b1111111111 %
1!
#60
0!
#61
b1111111111 %
1!
#62
0!
#63
b1111111111 %
1!
#64
0!
#65
b1111111111 %
1!
#66
0!
#67
b1111111111 %
1!
#68
0!
#69
b1111111111 %
1!
#70
0!
#71
b1111111111 %
1!
#72
0!
#73
b1111111111 %
1!
#74
0!
#75
b1111111111 %
1!
#76
0!
#77
b1111111111 %
1!
#78
0!
#79
b1111111111 %
1!
#80
0!
#81
b1111111111 %
1!
#82
0!
#83
b1111111111 %
1!
#84
0!
#85
b1111111111 %
1!
#86
0!
#87
b1111111111 %
1!
#88
0!
#89
b1111111111 %
1!
#90
0!
#91
b1111111111 %
1!
#92
0!
#93
b1111111111 %
1!
#94
0!
#95
b1111111111 %
1!
#96
0!
#97
b1111111111 %
1!
#98
0!
#99
b1111111111 %
1!
#100
0!
0#
#101
b111111111 %
1!
#102
0!
#103
b11111111 %
b111111111 $
1!
#104
0!
#105
b1111111 %
b11111111 $
1!
#106
0!
#107
b111111 %
b1111111 $
1!
#108
0!
#109
b11111 %
b111111 $
1!
#110
0!
#111
b1111 %
b11111 $
1!
#112
0!
#113
b111 %
b1111 $
1!
#114
0!
#115
b11 %
b111 $
1!
#116
0!
#117
b1 %
b11 $
1!
#118
0!
#119
b0 %
b1 $
1!
#120
0!
#121
b0 $
1!
#122
0!
#123
1!
#124
0!
#125
1!
#126
0!
#127
1!
#128
0!
#129
1!
#130
0!
#131
1!
#132
0!
#133
1!
#134
0!
#135
1!
#136
0!
#137
1!
#138
0!
#139
1!
#140
0!
1#
#141
b1000000000 %
1!
#142
0!
#143
b1100000000 %
b1000000000 $
1!
#144
0!
#145
b1110000000 %
b1100000000 $
1!
#146
0!
#147
b1111000000 %
b1110000000 $
1!
#148
0!
#149
b1111100000 %
b1111000000 $
1!
#150
0!
#151
b1111110000 %
b1111100000 $
1!
#152
0!
#153
b1111111000 %
b1111110000 $
1!
#154
0!
#155
b1111111100 %
b1111111000 $
1!
#156
0!
#157
b1111111110 %
b1111111100 $
1!
#158
0!
#159
b1111111111 %
b1111111110 $
1!
#160
0!
#161
b1111111111 %
b1111111111 $
1!
#162
0!
#163
b1111111111 %
1!
#164
0!
#165
b1111111111 %
1!
#166
0!
#167
b1111111111 %
1!
#168
0!
#169
b1111111111 %
1!
#170
0!
#171
b1111111111 %
1!
#172
0!
#173
b1111111111 %
1!
#174
0!
#175
b1111111111 %
1!
#176
0!
#177
b1111111111 %
1!
#178
0!
#179
b1111111111 %
1!
#180
0!
#181
b1111111111 %
1!
#182
0!
#183
b1111111111 %
1!
#184
0!
#185
b1111111111 %
1!
#186
0!
#187
b1111111111 %
1!
#188
0!
#189
b1111111111 %
1!
#190
0!
#191
b1111111111 %
1!
#192
0!
#193
b1111111111 %
1!
#194
0!
#195
b1111111111 %
1!
#196
0!
#197
b1111111111 %
1!
#198
0!
#199
b1111111111 %
1!
#200
0!
#201
b1111111111 %
1!
#202
0!
#203
b1111111111 %
1!
#204
0!
#205
b1111111111 %
1!
#206
0!
#207
b1111111111 %
1!
#208
0!
#209
b1111111111 %
1!
#210
0!
#211
b1111111111 %
1!
#212
0!
#213
b1111111111 %
1!
#214
0!
#215
b1111111111 %
1!
#216
0!
#217
b1111111111 %
1!
#218
0!
#219
b1111111111 %
1!
#220
0!
#221
b1111111111 %
1!
#222
0!
#223
b1111111111 %
1!
#224
0!
#225
b1111111111 %
1!
#226
0!
#227
b1111111111 %
1!
#228
0!
#229
b1111111111 %
1!
#230
0!
#231
b1111111111 %
1!
#232
0!
#233
b1111111111 %
1!
#234
0!
#235
b1111111111 %
1!
#236
0!
#237
b1111111111 %
1!
#238
0!
#239
b1111111111 %
1!
#240
0!
#241
b1111111111 %
1!
#242
0!
#243
b1111111111 %
1!
#244
0!
#245
b1111111111 %
1!
#246
0!
#247
b1111111111 %
1!
#248
0!
#249
b1111111111 %
1!
