PMA/mux_sipo.v
/*
******************************************************************************
*
*  Filename     :   mux_sipo.v
*i
*  Description  :   This module describes the multiplexer which passes dat to the input
                    of the sipo module. This mux is governed by EWRAP control signal and passes
                    data from two inputs: PMD_UNITDATA_indication and s_out which is the output of piso module
*
*  Author       :   Jhon Gaitan Aguilar
*                   <JHON.GAITAN@ucr.ac.cr>
*
*  License      :   This program is free software: you can redistribute it and/or modify
*                   it under the terms of the GNU General Public License as published by
*                   the Free Software Foundation, either version 3 of the License, or
*                   (at your option) any later version.
*
*                   This program is distributed in the hope that it will be useful,
*                   but WITHOUT ANY WARRANTY; without even the implied warranty of
*                   MERCHANTABILITY or FITNESS FOR A PARTICULAR PURPOSE.  See the
*                   GNU General Public License for more details.
*
*                   You should have received a copy of the GNU General Public License
*                   along with this program.  If not, see <http://www.gnu.org/licenses/>.
*  
*  Created      :   11/18/2022
*
******************************************************************************
*/
module mux_sipo(

    //Declare Inputs here
    input serial_sipo,
    input PMD_UNITDATA_indication,
    input EWRAP,
    //Declare Outputs here
    output reg mux_sipo_out);

//Declare registers here

//Declare wires here


always @(serial_sipo,PMD_UNITDATA_indication,EWRAP) begin
    if (EWRAP == 1) begin
     mux_sipo_out = serial_sipo;
    end
else
     mux_sipo_out = PMD_UNITDATA_indication;
end
endmodule

PMA/mux_piso.v
/*
******************************************************************************
*
*  Filename     :   mux_piso.v
*i
*  Description  :   This module describes a multiplexer which passes data to 
                    PMD_UNITDATA_request. This mux is governed by EWRAP control signal and passes
                    data from two inputs: s_out which is the output of piso module and which is the output of piso module
                    and zeros which is 0's vector when EWRAP is diabled.
*
*  Author       :   Jhon Gaitan Aguilar
*                   <JHON.GAITAN@ucr.ac.cr>
*
*  License      :   This program is free software: you can redistribute it and/or modify
*                   it under the terms of the GNU General Public License as published by
*                   the Free Software Foundation, either version 3 of the License, or
*                   (at your option) any later version.
*
*                   This program is distributed in the hope that it will be useful,
*                   but WITHOUT ANY WARRANTY; without even the implied warranty of
*                   MERCHANTABILITY or FITNESS FOR A PARTICULAR PURPOSE.  See the
*                   GNU General Public License for more details.
*
*                   You should have received a copy of the GNU General Public License
*                   along with this program.  If not, see <http://www.gnu.org/licenses/>.
*  
*  Created      :   11/18/2022
*
******************************************************************************
*/
module mux_piso(
    //Declare Inputs here
    input serial,
    input zeros,
    input  EWRAP,
    //Declare Outputs here
    output reg PMD_UNITDATA_request);
//Declare registers here

//Declare wires here

always @(serial,zeros,EWRAP) begin
    if (EWRAP == 1) begin
     PMD_UNITDATA_request = serial;
    end
else
     PMD_UNITDATA_request = zeros;
end
endmodule

PMA/sipo.v
/*
******************************************************************************
*
*  Filename     :   sipo.v
*i
*  Description  :   This module takes a serial input and generates parallel output.
                    For this module I adjoin a testbench together with its stimulations 
                    referenced as "sipo_tb.v" to output a vvp file and checking its functionality.
*
*  Author       :   Jhon Gaitan Aguilar
*                   <JHON.GAITAN@ucr.ac.cr>
*
*  License      :   This program is free software: you can redistribute it and/or modify
*                   it under the terms of the GNU General Public License as published by
*                   the Free Software Foundation, either version 3 of the License, or
*                   (at your option) any later version.
*
*                   This program is distributed in the hope that it will be useful,
*                   but WITHOUT ANY WARRANTY; without even the implied warranty of
*                   MERCHANTABILITY or FITNESS FOR A PARTICULAR PURPOSE.  See the
*                   GNU General Public License for more details.
*
*                   You should have received a copy of the GNU General Public License
*                   along with this program.  If not, see <http://www.gnu.org/licenses/>.
*  
*  Created      :   11/18/2022
*
******************************************************************************
*/
module sipo(
//Declare Inputs here
    input clk, //A global variable that works in the whole circuit.
    input reset,//A control signal of this module
    input s_in,
    //Desclare Outputs here
    output reg[9:0]parallel_out); //This is the parallel bitstream coming from rx_code-group
//Declare parameters here

//Declare Regsiters here
reg [9:0] temp_2;// A  shift register that stores the bits to output as parallel bistream.
//Declare Wires here 
//sesisbility list
always @(posedge clk) begin
    if (reset == 1)
    //Write to output
    parallel_out <= 10'b0;

    else if(reset == 0)begin
      temp_2 <= temp_2>>1;
      temp_2[9] <= s_in;//From [9] fill out with serialIinput inpit (s_in)||||tx_bit
    end
    if (temp_2[0] == 1'b0 || temp_2[0] == 1'b1) begin
        parallel_out = temp_2; 
    end
end
endmodule

PMA/piso.v


/*
******************************************************************************
*
*  Filename     :   piso.v
*i
*  Description  :   This module takes a parallel input and generates serial output.
                    For this module I adjoin a testbench together with its stimulations 
                    referenced as "piso_tb.v" to output a vvp file and check its functionality.
*
*  Author       :   Jhon Gaitan Aguilar
*                   <JHON.GAITAN@ucr.ac.cr>
*
*  License      :   This program is free software: you can redistribute it and/or modify
*                   it under the terms of the GNU General Public License as published by
*                   the Free Software Foundation, either version 3 of the License, or
*                   (at your option) any later version.
*
*                   This program is distributed in the hope that it will be useful,
*                   but WITHOUT ANY WARRANTY; without even the implied warranty of
*                   MERCHANTABILITY or FITNESS FOR A PARTICULAR PURPOSE.  See the
*                   GNU General Public License for more details.
*
*                   You should have received a copy of the GNU General Public License
*                   along with this program.  If not, see <http://www.gnu.org/licenses/>.
*  
*  Created      :   11/18/2022
*
******************************************************************************
*/
module piso(
    //Declare Inputs here
    input clk, //A global variable that works in the whole circuit.
    input reset,//A control signal of this module
    input [9:0]parallel_in, //This is the parallel bitstream coming from tx_code-group
    input s_start,
    //Desclare Outputs here
    output reg s_out);//This is the serial output chain towards pmd_unitdata.request

//Declare parameters here
localparam length = 10;//Length of the vector. in this case is 10-bit vector from PCS sublayer
//Declare Regsiters here
reg [9:0] temp;// A shift register that stores the bits to output as serial bistream.
//Declare Wires here 

//sesibility list
always @(posedge clk) begin
    //Set input to LOW
    if (reset==1)begin
        s_out = 0;
        temp = parallel_in;
    end
    else if(s_start == 1)begin
        s_out = temp[9];
        temp = {temp[9:0], 1'b0};
    end
end
endmodule

PMA/TBI.v
/*
******************************************************************************
*
*  Filename     :   TBI.v
*i
*  Description  :   The ten-bit interface (TBI) is defined to provide compatibility among 
                    devices designed by different manufacturers.
*
*  Author       :   Jhon Gaitan Aguilar
*                   <JHON.GAITAN@ucr.ac.cr>
*
*  License      :   This program is free software: you can redistribute it and/or modify
*                   it under the terms of the GNU General Public License as published by
*                   the Free Software Foundation, either version 3 of the License, or
*                   (at your option) any later version.
*
*                   This program is distributed in the hope that it will be useful,
*                   but WITHOUT ANY WARRANTY; without even the implied warranty of
*                   MERCHANTABILITY or FITNESS FOR A PARTICULAR PURPOSE.  See the
*                   GNU General Public License for more details.
*
*                   You should have received a copy of the GNU General Public License
*                   along with this program.  If not, see <http://www.gnu.org/licenses/>.
*  
*  Created      :   11/18/2022
*
******************************************************************************
*/
`include "piso.v"
`include "sipo.v"
`include "mux_sipo.v"
`include "mux_piso.v"

module TBI;
    //Global params
    reg clk;
    reg reset;
    //PISO variables
    reg s_start;
    reg [9:0]parallel_in;
    reg [9:0]temp;
    wire s_out;
    //SIPO variables
    reg s_in;
    reg [9:0]temp_2;
    wire [9:0]parallel_out;
    //MUX_piso
    reg serial;
    reg zeros;
    wire PMD_UNITDATA_request;
    //MUX global
    reg EWRAP;
    //MUX SIPO
    wire PMD_UNITDATA_indication;
    wire mux_sipo_out;
    reg serial_piso;
    piso uut1(
        .clk (clk),
        .reset (reset),
        .s_start (s_start),
        .parallel_in (parallel_in),
        .s_out (s_out)
    );
    sipo uut2(
        .clk (clk),
        .reset (reset),
        .parallel_out (parallel_out),
        .s_in (mux_sipo_out)
    );
    mux_piso uut3(
        .serial (s_out),
        .zeros (zeros),
        .EWRAP (EWRAP),
        .PMD_UNITDATA_request (PMD_UNITDATA_request)
    );
    mux_sipo uut4(
        .serial_sipo (s_out),
        .PMD_UNITDATA_indication (PMD_UNITDATA_indication),
        .EWRAP (EWRAP),
        .mux_sipo_out (mux_sipo_out)
    );
initial  begin
    $dumpfile("TBI.vcd");
	$dumpvars(-1, uut1);
    $dumpvars(-1, uut2);
    $dumpvars(-1, uut3);
    $dumpvars(-1, uut4);
    
end

always begin
 #5 clk = ~clk;
end
initial begin
    s_start = 0;
    clk = 1;
    s_in =1;
    zeros =0;
    EWRAP =0;
    #10 parallel_in = 10'b1010101111;
    #10 EWRAP = 1;
    reset = 1;
    #10 reset =0; s_start =1;
    //#2 S_START =1;
    //hasta aqui piso
    #20 s_in = 1;
    #20 s_in = 1;
    #20 s_in = 1;
    #20 s_in = 0;
    #20 s_in = 0;
    //#20 ewrap = 1;
    #20 s_in = 1;
    #20 s_in = 0;
    #20 s_in = 1;
    #20 s_in = 0;
    #20 s_in = 1;
end
initial #1000 $finish;
endmodule

PMA/TBI.vcd
$date
	Sun Nov 20 23:35:08 2022
$end
$version
	Icarus Verilog
$end
$timescale
	1s
$end
$scope module TBI $end
$scope module uut1 $end
$var wire 1 ! clk $end
$var wire 10 " parallel_in [9:0] $end
$var wire 1 # reset $end
$var wire 1 $ s_start $end
$var reg 1 % s_out $end
$var reg 10 & temp [9:0] $end
$upscope $end
$upscope $end
$scope module TBI $end
$scope module uut2 $end
$var wire 1 ! clk $end
$var wire 1 # reset $end
$var wire 1 ' s_in $end
$var reg 10 ( parallel_out [9:0] $end
$var reg 10 ) temp_2 [9:0] $end
$upscope $end
$upscope $end
$scope module TBI $end
$scope module uut3 $end
$var wire 1 * EWRAP $end
$var wire 1 % serial $end
$var wire 1 + zeros $end
$var reg 1 , PMD_UNITDATA_request $end
$upscope $end
$upscope $end
$scope module TBI $end
$scope module uut4 $end
$var wire 1 * EWRAP $end
$var wire 1 - PMD_UNITDATA_indication $end
$var wire 1 % serial_sipo $end
$var reg 1 ' mux_sipo_out $end
$upscope $end
$upscope $end
$enddefinitions $end
#0
$dumpvars
z-
0,
0+
0*
bx )
bx (
z'
bx &
x%
0$
x#
bx "
1!
$end
#5
0!
#10
1!
b1010101111 "
#15
0!
#20
b0 (
b1010101111 &
0%
0,
0'
1!
1#
1*
#25
0!
#30
b0xxxxxxxxx )
1,
1'
b101011110 &
1%
1!
1$
0#
#35
0!
#40
b10xxxxxxxx )
0,
0'
b1010111100 &
0%
1!
#45
0!
#50
b10xxxxxxx )
1,
1'
b101111000 &
1%
1!
#55
0!
#60
b1010xxxxxx )
0,
0'
b1011110000 &
0%
1!
#65
0!
#70
b1010xxxxx )
1,
1'
b111100000 &
1%
1!
#75
0!
#80
b101010xxxx )
0,
0'
b1111000000 &
0%
1!
#85
0!
#90
b101010xxx )
1,
1'
b1110000000 &
1%
1!
#95
0!
#100
b10101010xx )
b1100000000 &
1!
#105
0!
#110
b110101010x )
b1000000000 &
1!
#115
0!
#120
b1110101010 )
b0 &
1!
#125
0!
#130
b1111010101 )
0,
0'
b1110101010 (
0%
1!
#135
0!
#140
b111101010 )
b1111010101 (
1!
#145
0!
#150
b11110101 )
b111101010 (
1!
#155
0!
#160
b1111010 )
b11110101 (
1!
#165
0!
#170
b111101 )
b1111010 (
1!
#175
0!
#180
b11110 )
b111101 (
1!
#185
0!
#190
b1111 )
b11110 (
1!
#195
0!
#200
b111 )
b1111 (
1!
#205
0!
#210
b11 )
b111 (
1!
#215
0!
#220
b1 )
b11 (
1!
#225
0!
#230
b0 )
b1 (
1!
#235
0!
#240
b0 (
1!
